django_telegram_login/__init__.py
django_telegram_login/apps.py
django_telegram_login/authentication.py
django_telegram_login/errors.py
django_telegram_login/tests.py
django_telegram_login/widgets/__init__.py
django_telegram_login/widgets/constants.py
django_telegram_login/widgets/generator.py
django_telegram_login-0.2.3.dist-info/DESCRIPTION.rst
django_telegram_login-0.2.3.dist-info/METADATA
django_telegram_login-0.2.3.dist-info/RECORD
django_telegram_login-0.2.3.dist-info/WHEEL
django_telegram_login-0.2.3.dist-info/metadata.json
django_telegram_login-0.2.3.dist-info/top_level.txt
