Metadata-Version: 1.1
Name: django-telegram-login
Version: 0.2.3
Summary: The reusable Django application for Telegram authorization (also known as Telegram login).
Home-page: https://github.com/dmytrostriletskyi/django-telegram-login
Author: Dmytro Striletskyi
Author-email: dmytro.striletskyi@gmail.com
License: MIT
Platform: UNKNOWN
Classifier: Environment :: Web Environment
Classifier: Framework :: Django
Classifier: Intended Audience :: Developers
Classifier: License :: OSI Approved :: MIT License
Classifier: Operating System :: OS Independent
Classifier: Programming Language :: Python
Classifier: Programming Language :: Python :: 3.5
Classifier: Programming Language :: Python :: 3.6
Classifier: Topic :: Internet :: WWW/HTTP
Classifier: Topic :: Internet :: WWW/HTTP :: Dynamic Content
